django_includes/__init__.py
django_includes/_version.py
django_includes/jinja2.py
django_includes/middleware.py
django_includes/settings.py
django_includes/static/hinclude.js
django_includes/utils.py
django_includes/views.py
django_includes-1.0.0.dist-info/LICENSE
django_includes-1.0.0.dist-info/METADATA
django_includes-1.0.0.dist-info/WHEEL
django_includes-1.0.0.dist-info/RECORD
