Metadata-Version: 2.1
Name: django-includes
Version: 1.0.0
Summary: 
Author: Romain Dorgueil
Author-email: romain@makersquad.fr
Requires-Python: >=3.10,<4.0
Classifier: Programming Language :: Python :: 3
Classifier: Programming Language :: Python :: 3.10
Classifier: Programming Language :: Python :: 3.11
Classifier: Programming Language :: Python :: 3.12
Requires-Dist: django (>=4.2,<5.1)
Requires-Dist: jinja2 (>=3.1.4,<4.0.0)
Requires-Dist: pyjwt (>2,<3)
Requires-Dist: pytz (>=2024.1)
Requires-Dist: requests (>=2.31,<3)
